whatpack/asyncpy/__init__.py
whatpack/asyncpy/whats.py
whatpack/asyncpy/core/__init__.py
whatpack/asyncpy/core/core_.py
whatpack/asyncpy/core/exceptions.py
whatpack/headless/__init__.py
whatpack/headless/app.py
whatpack/headless/whats.py
whatpack/sync/__init__.py
whatpack/sync/whats.py
whatpack/sync/core/__init__.py
whatpack/sync/core/core_.py
whatpack/sync/core/exceptions.py
whatpack.py-0.0.2.3.dist-info/LICENSE
whatpack.py-0.0.2.3.dist-info/METADATA
whatpack.py-0.0.2.3.dist-info/WHEEL
whatpack.py-0.0.2.3.dist-info/top_level.txt
whatpack.py-0.0.2.3.dist-info/RECORD
