Metadata-Version: 2.1
Name: whatpack.py
Version: 0.0.2.3
Summary: About whatpack.py is a Python package that
Home-page: https://github.com/SigireddyBalasai/whatpack.py
Download-URL: https://github.com/SigireddyBalasai/whatpack.py
Author: SigireddyBalasai
Author-email: sigireddybalasai@gmail.com
Maintainer: SigireddyBalasai
Maintainer-email: SigireddyBalasai@gmail.com
License: MIT
Keywords: send_what_msg,whatpack
Classifier: Development Status :: 5 - Production/Stable
Classifier: Intended Audience :: Developers
Classifier: Topic :: Software Development :: Build Tools
Classifier: License :: OSI Approved :: MIT License
Classifier: Programming Language :: Python :: 3.8
Classifier: Programming Language :: Python :: 3.9
Classifier: Programming Language :: Python :: 3.10
Classifier: Programming Language :: Python :: 3.11
License-File: LICENSE
Requires-Dist: flask
Requires-Dist: selenium
Requires-Dist: pyperclip
Requires-Dist: pyautogui
Requires-Dist: aiohttp
Requires-Dist: pyscreeze
Requires-Dist: opencv-python
Requires-Dist: numpy
Requires-Dist: keyboard
Requires-Dist: requests
